MANIFEST.in
README.md
setup.py
django_wechatvote.egg-info/PKG-INFO
django_wechatvote.egg-info/SOURCES.txt
django_wechatvote.egg-info/dependency_links.txt
django_wechatvote.egg-info/requires.txt
django_wechatvote.egg-info/top_level.txt
django_wechatvote.egg-info/zip-safe
vote/__init__.py
vote/admin.py
vote/common.py
vote/models.py
vote/modelsResource.py
vote/tests.py
vote/urls_api.py
vote/urls_tmp.py
vote/views.py
vote/qiniustorage/__init__.py
vote/qiniustorage/backends.py
vote/qiniustorage/utils.py
vote/static/vote/css/vote.css
vote/static/vote/img/loading.gif
vote/static/vote/img/next.png
vote/static/vote/img/partake.png
vote/static/vote/img/ranking.png
vote/static/vote/img/ranking_list.png
vote/static/vote/img/share.png
vote/static/vote/img/share_icon.png
vote/static/vote/img/vote.png
vote/static/vote/img/vote_bg.png
vote/static/vote/js/baiduTemplate.js
vote/static/vote/js/jquery-1.9.1.js
vote/static/vote/js/jquery-1.9.1.min.js
vote/static/vote/js/vote.js
vote/static/vote/js/weixin.1.0.0.js
vote/templates/vote/vote_activity_index.html
vote/templates/vote/vote_base.html
vote/templates/vote/vote_product_createform.html
vote/templates/vote/vote_product_index.html
vote/templates/vote/vote_products_list.html
vote/wechat_lib/__init__.py
vote/wechat_lib/wechat_api.py
vote/wechat_lib/wechat_conf.py
vote/wechat_lib/wechat_decorators.py
vote/wechat_lib/wechat_utils.py
vote/wechat_lib/wechat_sdk_extension/__init__.py