Metadata-Version: 1.0
Name: django-wechatvote
Version: 0.0.5
Summary: this is a package for django wechat vote
Home-page: https://github.com/minkedong/django_wechatvote
Author: minkedong
Author-email: minkedong89@126.com
License: Free
Keywords: django vote wechat
Platform: UNKNOWN
